README.md
setup.py
pnmlib/__init__.py
pnmlib.egg-info/PKG-INFO
pnmlib.egg-info/SOURCES.txt
pnmlib.egg-info/dependency_links.txt
pnmlib.egg-info/requires.txt
pnmlib.egg-info/top_level.txt
pnmlib/core/__init__.py
pnmlib/core/_admin.py
pnmlib/core/_funcs.py
pnmlib/generators/__init__.py
pnmlib/generators/_bcc.py
pnmlib/generators/_cubic.py
pnmlib/generators/_delaunay.py
pnmlib/generators/_fcc.py
pnmlib/generators/_gabriel.py
pnmlib/generators/_template.py
pnmlib/generators/_voronoi.py
pnmlib/generators/_voronoi_delaunay_dual.py
pnmlib/generators/tools/__init__.py
pnmlib/generators/tools/_funcs.py
pnmlib/inspect/__init__.py
pnmlib/inspect/_funcs.py
pnmlib/io/__init__.py
pnmlib/io/_funcs.py
pnmlib/models/__init__.py
pnmlib/models/_funcs.py
pnmlib/models/geometry/__init__.py
pnmlib/models/geometry/_funcs.py
pnmlib/models/physics/__init__.py
pnmlib/models/physics/_funcs.py
pnmlib/operations/__init__.py
pnmlib/operations/_binary.py
pnmlib/operations/_funcs.py
pnmlib/operations/_unary.py
pnmlib/queries/__init__.py
pnmlib/queries/_funcs.py
pnmlib/queries/_qupc.py
pnmlib/simulations/__init__.py
pnmlib/simulations/_funcs.py
pnmlib/simulations/_percolation.py
pnmlib/simulations/_transport.py
pnmlib/tools/__init__.py
pnmlib/tools/_coords.py
pnmlib/tools/_funcs.py
pnmlib/utils/__init__.py
pnmlib/utils/_funcs.py
pnmlib/visualization/__init__.py
pnmlib/visualization/_funcs.py