Metadata-Version: 2.1
Name: pnmlib
Version: 0.0.1
Summary: A library of pore netwwork modeling functions
Home-page: http://pmeal.com
Download-URL: https://www.pmeal.com/
Author: PMEAL Team
Author-email: jgostick@uwaterloo.ca
